symd/__init__.py
symd/groups.py
symd/main.py
symd/symd.py
symd/version.py
symd/data/2dgroups.json
symd/data/3dgroups.json
symd-1.1.3.dist-info/METADATA
symd-1.1.3.dist-info/WHEEL
symd-1.1.3.dist-info/entry_points.txt
symd-1.1.3.dist-info/top_level.txt
symd-1.1.3.dist-info/RECORD
