Metadata-Version: 2.1
Name: symd
Version: 1.1.3
Summary: Symmetric Molecular Dynamics
Home-page: https://whitead.github.io/symd/
Author: Andrew White
Author-email: andrew.white@rochester.edu
License: MIT
Classifier: Programming Language :: Python :: 3
Classifier: License :: OSI Approved :: MIT License
Classifier: Operating System :: OS Independent
Classifier: Topic :: Scientific/Engineering :: Chemistry
Requires-Dist: numpy
Requires-Dist: click
